terra_notebook_utils/__init__.py
terra_notebook_utils/azure_auth.py
terra_notebook_utils/costs.py
terra_notebook_utils/drs.py
terra_notebook_utils/gs.py
terra_notebook_utils/http.py
terra_notebook_utils/logger.py
terra_notebook_utils/profile.py
terra_notebook_utils/table.py
terra_notebook_utils/tar_gz.py
terra_notebook_utils/terra_auth.py
terra_notebook_utils/utils.py
terra_notebook_utils/vcf.py
terra_notebook_utils/version.py
terra_notebook_utils/workflows.py
terra_notebook_utils/workspace.py
terra_notebook_utils/xprofile.py
terra_notebook_utils/blobstore/__init__.py
terra_notebook_utils/blobstore/copy_client.py
terra_notebook_utils/blobstore/gs.py
terra_notebook_utils/blobstore/local.py
terra_notebook_utils/blobstore/progress.py
terra_notebook_utils/blobstore/url.py
terra_notebook_utils/cli/__init__.py
terra_notebook_utils/cli/main.py
terra_notebook_utils/cli/commands/__init__.py
terra_notebook_utils/cli/commands/config.py
terra_notebook_utils/cli/commands/drs.py
terra_notebook_utils/cli/commands/profile.py
terra_notebook_utils/cli/commands/table.py
terra_notebook_utils/cli/commands/vcf.py
terra_notebook_utils/cli/commands/workflows.py
terra_notebook_utils/cli/commands/workspace.py
tests/infra/__init__.py
tests/infra/partialize_vcf.py
tests/infra/server.py
tests/infra/testmode.py
terra_notebook_utils-0.12.0.dist-info/LICENSE
terra_notebook_utils-0.12.0.dist-info/METADATA
terra_notebook_utils-0.12.0.dist-info/WHEEL
terra_notebook_utils-0.12.0.dist-info/entry_points.txt
terra_notebook_utils-0.12.0.dist-info/top_level.txt
terra_notebook_utils-0.12.0.dist-info/RECORD
