Metadata-Version: 2.1
Name: terra-notebook-utils
Version: 0.12.0
Summary: Utilities for the Terra notebook environment.
Home-page: https://github.com/DataBiosphere/terra-notebook-utils
Author: Brian Hannafious
Author-email: bhannafi@ucsc.edu
License: MIT
Platform: MacOS X
Platform: Posix
Classifier: Intended Audience :: Science/Research
Classifier: License :: OSI Approved :: MIT License
Classifier: Programming Language :: Python :: 3.7
License-File: LICENSE
Requires-Dist: azure-identity (<2,>=1.12.0)
Requires-Dist: google-cloud-storage (<2,>=1.38.0)
Requires-Dist: gs-chunked-io (<0.6,>=0.5.1)
Requires-Dist: firecloud
Requires-Dist: bgzip (<0.4,>=0.3.5)
Requires-Dist: cli-builder (<0.2,>=0.1.5)
Requires-Dist: oauth2client
Requires-Dist: jmespath (==0.10.0)
Requires-Dist: getm (<0.1.0,>=0.0.4)
Requires-Dist: jsonschema
